LICENSE
p115tiny302/__init__.py
p115tiny302/__main__.py
p115tiny302/app.py
p115tiny302/py.typed
p115tiny302-0.2.2.dist-info/LICENSE
p115tiny302-0.2.2.dist-info/LICENSE_zh
p115tiny302-0.2.2.dist-info/METADATA
p115tiny302-0.2.2.dist-info/WHEEL
p115tiny302-0.2.2.dist-info/entry_points.txt
p115tiny302-0.2.2.dist-info/RECORD
