Metadata-Version: 2.1
Name: p115tiny302
Version: 0.2.2
Summary: 115 tiny 302 backend.
Home-page: https://github.com/ChenyangGao/p115client/tree/main/modules/p115tiny302
License: MIT
Keywords: python-115,302,backend
Author: ChenyangGao
Author-email: wosiwujm@gmail.com
Requires-Python: >=3.12,<4.0
Classifier: Development Status :: 5 - Production/Stable
Classifier: Intended Audience :: Developers
Classifier: License :: OSI Approved :: MIT License
Classifier: Operating System :: OS Independent
Classifier: Programming Language :: Python
Classifier: Programming Language :: Python :: 3
Classifier: Programming Language :: Python :: 3.12
Classifier: Programming Language :: Python :: 3.13
Classifier: Programming Language :: Python :: 3 :: Only
Classifier: Topic :: Software Development
Classifier: Topic :: Software Development :: Libraries
Classifier: Topic :: Software Development :: Libraries :: Python Modules
Requires-Dist: blacksheep
Requires-Dist: blacksheep-rich-log (>=0.0.1)
Requires-Dist: cachedict (>=0.0.6)
Requires-Dist: orjson
Requires-Dist: p115client (>=0.0.6.10)
Requires-Dist: p115pickcode (>=0.0.5.4)
Requires-Dist: posixpatht (>=0.0.4)
Requires-Dist: python-dicttools (>=0.0.4)
Requires-Dist: pyyaml
Requires-Dist: uvicorn
Project-URL: Repository, https://github.com/ChenyangGao/p115client/tree/main/modules/p115tiny302
